epics_containers_cli/__init__.py
epics_containers_cli/__main__.py
epics_containers_cli/_version.py
epics_containers_cli/docker.py
epics_containers_cli/git.py
epics_containers_cli/globals.py
epics_containers_cli/logging.py
epics_containers_cli/shell.py
epics_containers_cli/utils.py
epics_containers_cli/dev/__init__.py
epics_containers_cli/dev/dev_cli.py
epics_containers_cli/dev/dev_commands.py
epics_containers_cli/ioc/__init__.py
epics_containers_cli/ioc/helm.py
epics_containers_cli/ioc/ioc_autocomplete.py
epics_containers_cli/ioc/ioc_cli.py
epics_containers_cli/ioc/k8s_commands.py
epics_containers_cli/ioc/local_commands.py
epics_containers_cli/k8s/k8s_cli.py
epics_containers_cli/k8s/k8s_commands.py
epics_containers_cli/k8s/kubectl.py
epics_containers_cli-2.7.0.dist-info/LICENSE
epics_containers_cli-2.7.0.dist-info/METADATA
epics_containers_cli-2.7.0.dist-info/WHEEL
epics_containers_cli-2.7.0.dist-info/entry_points.txt
epics_containers_cli-2.7.0.dist-info/top_level.txt
epics_containers_cli-2.7.0.dist-info/RECORD
