Metadata-Version: 2.1
Name: epics-containers-cli
Version: 2.7.0
Summary: One line description of your module
Author-email: Giles Knap <giles.knap@diamond.ac.uk>
License: Apache License
Project-URL: GitHub, https://github.com/epics-containers/epics-containers-cli
Classifier: Development Status :: 3 - Alpha
Classifier: License :: OSI Approved :: Apache Software License
Classifier: Programming Language :: Python :: 3.9
Classifier: Programming Language :: Python :: 3.10
Classifier: Programming Language :: Python :: 3.11
Requires-Python: >=3.9
License-File: LICENSE
Requires-Dist: natsort
Requires-Dist: typer[all]
Requires-Dist: requests
Requires-Dist: ruamel.yaml
Requires-Dist: jinja2
Provides-Extra: dev
Requires-Dist: black ; extra == 'dev'
Requires-Dist: mock ; extra == 'dev'
Requires-Dist: mypy ; extra == 'dev'
Requires-Dist: pipdeptree ; extra == 'dev'
Requires-Dist: pre-commit ==3.6.0 ; extra == 'dev'
Requires-Dist: pydata-sphinx-theme >=0.12 ; extra == 'dev'
Requires-Dist: pytest ; extra == 'dev'
Requires-Dist: pytest-cov ; extra == 'dev'
Requires-Dist: pytest-mock ; extra == 'dev'
Requires-Dist: ruff ; extra == 'dev'
Requires-Dist: Sphinx ==6.2.1 ; extra == 'dev'
Requires-Dist: sphinx-autobuild ; extra == 'dev'
Requires-Dist: sphinx-copybutton ; extra == 'dev'
Requires-Dist: sphinx-design ; extra == 'dev'
Requires-Dist: tox-direct ; extra == 'dev'
Requires-Dist: types-mock ; extra == 'dev'
Requires-Dist: types-requests ; extra == 'dev'
